Anonymizer-ticket/__init__.py
Anonymizer-ticket/gradio_app.py
Anonymizer-ticket/utils.py
tests/__init__.py
tests/test_utils.py
Anonymizer_ticket-0.1.dist-info/METADATA
Anonymizer_ticket-0.1.dist-info/WHEEL
Anonymizer_ticket-0.1.dist-info/entry_points.txt
Anonymizer_ticket-0.1.dist-info/top_level.txt
Anonymizer_ticket-0.1.dist-info/RECORD
