Metadata-Version: 2.1
Name: Anonymizer-ticket
Version: 0.1
Requires-Python: >=3.7
Requires-Dist: transformers
Requires-Dist: torch
Requires-Dist: gradio
Requires-Dist: pandas
